[
  {
    "url": "https://www.chess.com/game/live/49680604629",
    "pgn": "[Event \"Live Chess\"]\n[Site \"Chess.com\"]\n[Date \"2022.06.22\"]\n[Round \"-\"]\n[White \"penguingm1\"]\n[Black \"0gZPanda\"]\n[Result \"0-1\"]\n[CurrentPosition \"4k3/pp3p1p/4pPpP/6q1/1P6/P1R1P3/3K4/8 w - -\"]\n[Timezone \"UTC\"]\n[ECO \"A45\"]\n[ECOUrl \"https://www.chess.com/openings/Indian-Game-Gibbins-Weidenhagen-Gambit\"]\n[UTCDate \"2022.06.22\"]\n[UTCTime \"23:49:40\"]\n[WhiteElo \"3202\"]\n[BlackElo \"3131\"]\n[TimeControl \"60\"]\n[Termination \"0gZPanda won by resignation\"]\n[StartTime \"23:49:40\"]\n[EndDate \"2022.06.22\"]\n[EndTime \"23:51:17\"]\n[Link \"https://www.chess.com/game/live/49680604629\"]\n\n1. d4 {[%clk 0:00:59.4]} 1... Nf6 {[%clk 0:00:59.2]} 2. g4 {[%clk 0:00:58.7]} 2... e6 {[%clk 0:00:58.8]} 3. g5 {[%clk 0:00:58.6]} 3... Nd5 {[%clk 0:00:58.3]} 4. c4 {[%clk 0:00:57.9]} 4... Nb6 {[%clk 0:00:58.1]} 5. c5 {[%clk 0:00:57.5]} 5... Nd5 {[%clk 0:00:56.2]} 6. e4 {[%clk 0:00:57.3]} 6... Ne7 {[%clk 0:00:55.8]} 7. Nc3 {[%clk 0:00:57]} 7... d6 {[%clk 0:00:53.8]} 8. cxd6 {[%clk 0:00:56.9]} 8... cxd6 {[%clk 0:00:53.3]} 9. Nf3 {[%clk 0:00:56.8]} 9... Nbc6 {[%clk 0:00:53]} 10. Bd3 {[%clk 0:00:56]} 10... g6 {[%clk 0:00:52.6]} 11. h4 {[%clk 0:00:55]} 11... Bg7 {[%clk 0:00:52.2]} 12. Be3 {[%clk 0:00:54.6]} 12... Nb4 {[%clk 0:00:51.7]} 13. Be2 {[%clk 0:00:53.4]} 13... Bd7 {[%clk 0:00:51.2]} 14. a3 {[%clk 0:00:53.2]} 14... Nbc6 {[%clk 0:00:50.5]} 15. h5 {[%clk 0:00:53.1]} 15... d5 {[%clk 0:00:49.6]} 16. h6 {[%clk 0:00:52.5]} 16... Bf8 {[%clk 0:00:49.2]} 17. Rc1 {[%clk 0:00:50.7]} 17... dxe4 {[%clk 0:00:48.2]} 18. Nxe4 {[%clk 0:00:50.6]} 18... Nd5 {[%clk 0:00:47.3]} 19. Qb3 {[%clk 0:00:49.3]} 19... Be7 {[%clk 0:00:46.7]} 20. Bd3 {[%clk 0:00:45.3]} 20... O-O {[%clk 0:00:45.2]} 21. Qc2 {[%clk 0:00:44.9]} 21... Rc8 {[%clk 0:00:44.5]} 22. Qd2 {[%clk 0:00:44.3]} 22... Qb6 {[%clk 0:00:42.4]} 23. O-O {[%clk 0:00:42.9]} 23... Na5 {[%clk 0:00:41.9]} 24. Rxc8 {[%clk 0:00:41.5]} 24... Rxc8 {[%clk 0:00:41.8]} 25. Bb1 {[%clk 0:00:40.8]} 25... Nb3 {[%clk 0:00:39.3]} 26. Qe2 {[%clk 0:00:40.3]} 26... Bb5 {[%clk 0:00:37.6]} 27. Bd3 {[%clk 0:00:39.5]} 27... Bxd3 {[%clk 0:00:36.3]} 28. Qxd3 {[%clk 0:00:39.4]} 28... Rd8 {[%clk 0:00:35.4]} 29. Ne5 {[%clk 0:00:38.9]} 29... Na5 {[%clk 0:00:34.2]} 30. b4 {[%clk 0:00:38.2]} 30... Nc6 {[%clk 0:00:33.6]} 31. Rd1 {[%clk 0:00:37.4]} 31... Nxe5 {[%clk 0:00:33]} 32. dxe5 {[%clk 0:00:37.3]} 32... Nxe3 {[%clk 0:00:32.3]} 33. fxe3 {[%clk 0:00:25.2]} 33... Rxd3 {[%clk 0:00:31.3]} 34. Rxd3 {[%clk 0:00:25.1]} 34... Qc7 {[%clk 0:00:30.6]} 35. Nf6+ {[%clk 0:00:23.6]} 35... Bxf6 {[%clk 0:00:28.8]} 36. exf6 {[%clk 0:00:23.5]} 36... Kf8 {[%clk 0:00:28.2]} 37. Kf1 {[%clk 0:00:21.6]} 37... Qc4 {[%clk 0:00:26.8]} 38. Ke2 {[%clk 0:00:20.9]} 38... Ke8 {[%clk 0:00:26.1]} 39. Kd2 {[%clk 0:00:20.8]} 39... Qg4 {[%clk 0:00:25.2]} 40. Rc3 {[%clk 0:00:20.7]} 40... Qxg5 {[%clk 0:00:24.3]} 0-1\n",
    "time_control": "60",
    "end_time": 1655941877,
    "rated": true,
    "accuracies": {
      "white": 81.78,
      "black": 85.85
    },
    "tcn": "lB!ToE0SEMTJkAJPAIPJmCJ0bsZRIRYRgv5Qft2UpF92cuQztm6ZiqzQFNRJNV29acJCsC0Jdr90mt8!rk46kl7PegQGc696tbGrlmZHbtHtmt67vKrGjzGQfdQKBKJunu7tdtPYCT0TKT!9gfYAfm98mlAEtsEM",
    "uuid": "02de5f72-f286-11ec-8e7a-78ac4409ff3c",
    "initial_setup": "rnbqkbnr/pppppppp/8/8/8/8/PPPPPPPP/RNBQKBNR w KQkq - 0 1",
    "fen": "4k3/pp3p1p/4pPpP/6q1/1P6/P1R1P3/3K4/8 w - -",
    "time_class": "bullet",
    "rules": "chess",
    "white": {
      "rating": 3202,
      "result": "resigned",
      "@id": "https://api.chess.com/pub/player/penguingm1",
      "username": "penguingm1",
      "uuid": "332537e0-d833-11e1-8022-000000000000"
    },
    "black": {
      "rating": 3131,
      "result": "win",
      "@id": "https://api.chess.com/pub/player/0gzpanda",
      "username": "0gZPanda",
      "uuid": "a52051ea-630e-11ea-88cb-478d6d4098ea"
    }
  },
  {
    "url": "https://www.chess.com/game/live/49680618805",
    "pgn": "[Event \"Live Chess\"]\n[Site \"Chess.com\"]\n[Date \"2022.06.22\"]\n[Round \"-\"]\n[White \"0gZPanda\"]\n[Black \"penguingm1\"]\n[Result \"0-1\"]\n[CurrentPosition \"8/p4b2/8/8/6kp/6p1/8/6K1 w - -\"]\n[Timezone \"UTC\"]\n[ECO \"C50\"]\n[ECOUrl \"https://www.chess.com/openings/Giuoco-Piano-Game-4.O-O-Nf6\"]\n[UTCDate \"2022.06.22\"]\n[UTCTime \"23:50:57\"]\n[WhiteElo \"3125\"]\n[BlackElo \"3210\"]\n[TimeControl \"60\"]\n[Termination \"penguingm1 won on time\"]\n[StartTime \"23:50:57\"]\n[EndDate \"2022.06.22\"]\n[EndTime \"23:53:21\"]\n[Link \"https://www.chess.com/game/live/49680618805\"]\n\n1. e4 {[%clk 0:01:00]} 1... e5 {[%clk 0:01:00]} 2. Nf3 {[%clk 0:00:59.5]} 2... Nc6 {[%clk 0:00:59.6]} 3. Bc4 {[%clk 0:00:59.3]} 3... Bc5 {[%clk 0:00:59.2]} 4. O-O {[%clk 0:00:58.4]} 4... Nf6 {[%clk 0:00:58.9]} 5. Re1 {[%clk 0:00:58]} 5... O-O {[%clk 0:00:58.4]} 6. c3 {[%clk 0:00:57.6]} 6... Nxe4 {[%clk 0:00:56.4]} 7. Rxe4 {[%clk 0:00:55.3]} 7... d5 {[%clk 0:00:55.8]} 8. Nxe5 {[%clk 0:00:49.8]} 8... dxe4 {[%clk 0:00:52.2]} 9. Nxf7 {[%clk 0:00:49.1]} 9... Bxf2+ {[%clk 0:00:41.3]} 10. Kxf2 {[%clk 0:00:48.1]} 10... Ne5 {[%clk 0:00:39.5]} 11. Kg1 {[%clk 0:00:45.4]} 11... Nxf7 {[%clk 0:00:37]} 12. d3 {[%clk 0:00:44.9]} 12... exd3 {[%clk 0:00:36]} 13. Bf4 {[%clk 0:00:41.4]} 13... Bf5 {[%clk 0:00:33.4]} 14. Nd2 {[%clk 0:00:40.5]} 14... Kh8 {[%clk 0:00:33]} 15. Qh5 {[%clk 0:00:39.9]} 15... Nd6 {[%clk 0:00:31.7]} 16. Bd5 {[%clk 0:00:37.5]} 16... Bg6 {[%clk 0:00:30.9]} 17. Qg4 {[%clk 0:00:37]} 17... c6 {[%clk 0:00:29.5]} 18. Bf3 {[%clk 0:00:36.1]} 18... Qb6+ {[%clk 0:00:28.4]} 19. Kh1 {[%clk 0:00:34.7]} 19... Qxb2 {[%clk 0:00:27.3]} 20. Rb1 {[%clk 0:00:34.4]} 20... Qxc3 {[%clk 0:00:26.8]} 21. h4 {[%clk 0:00:33]} 21... Nc4 {[%clk 0:00:23.4]} 22. h5 {[%clk 0:00:27.7]} 22... Bf5 {[%clk 0:00:22.5]} 23. Qg5 {[%clk 0:00:25.3]} 23... h6 {[%clk 0:00:22.1]} 24. Qe7 {[%clk 0:00:22.4]} 24... Rae8 {[%clk 0:00:19.1]} 25. Qc5 {[%clk 0:00:20.6]} 25... b5 {[%clk 0:00:16.9]} 26. Bxc6 {[%clk 0:00:19.7]} 26... Rc8 {[%clk 0:00:15.8]} 27. Nxc4 {[%clk 0:00:18.5]} 27... Qxc4 {[%clk 0:00:15]} 28. Qxc4 {[%clk 0:00:16.1]} 28... bxc4 {[%clk 0:00:14.9]} 29. Bb5 {[%clk 0:00:15.6]} 29... d2 {[%clk 0:00:14.4]} 30. Bxd2 {[%clk 0:00:14.9]} 30... Bxb1 {[%clk 0:00:13.6]} 31. Bc3 {[%clk 0:00:14.6]} 31... Rf5 {[%clk 0:00:12.3]} 32. Bd7 {[%clk 0:00:13.8]} 32... Rxh5+ {[%clk 0:00:11.9]} 33. Kg1 {[%clk 0:00:13.6]} 33... Bf5 {[%clk 0:00:11.4]} 34. Bb5 {[%clk 0:00:12.3]} 34... Be6 {[%clk 0:00:10.4]} 35. Ba6 {[%clk 0:00:11.3]} 35... Rg5 {[%clk 0:00:10.3]} 36. Bxc8 {[%clk 0:00:10.7]} 36... Bxc8 {[%clk 0:00:10.2]} 37. Kf2 {[%clk 0:00:10.1]} 37... Rg6 {[%clk 0:00:10.1]} 38. g3 {[%clk 0:00:10]} 38... Bb7 {[%clk 0:00:10]} 39. Ke3 {[%clk 0:00:09.8]} 39... Ra6 {[%clk 0:00:09.4]} 40. Kd4 {[%clk 0:00:09.7]} 40... Rxa2 {[%clk 0:00:09.3]} 41. Kxc4 {[%clk 0:00:09.6]} 41... Rg2 {[%clk 0:00:09]} 42. Bd4 {[%clk 0:00:09.4]} 42... Rxg3 {[%clk 0:00:08.7]} 43. Be5 {[%clk 0:00:09.3]} 43... Rg4+ {[%clk 0:00:08.6]} 44. Kc5 {[%clk 0:00:08.7]} 44... Kh7 {[%clk 0:00:08.5]} 45. Kd6 {[%clk 0:00:08.2]} 45... h5 {[%clk 0:00:08.4]} 46. Bd4 {[%clk 0:00:08.1]} 46... Bc8 {[%clk 0:00:08.3]} 47. Be5 {[%clk 0:00:07.7]} 47... Bf5 {[%clk 0:00:08.2]} 48. Bf4 {[%clk 0:00:07.6]} 48... Bg6 {[%clk 0:00:08.1]} 49. Ke5 {[%clk 0:00:07.4]} 49... Rxf4 {[%clk 0:00:07.7]} 50. Kxf4 {[%clk 0:00:06.7]} 50... Kh6 {[%clk 0:00:07.6]} 51. Kg3 {[%clk 0:00:06.1]} 51... Bf7 {[%clk 0:00:07.5]} 52. Kh3 {[%clk 0:00:06]} 52... g5 {[%clk 0:00:07.4]} 53. Kg3 {[%clk 0:00:05.9]} 53... Kg6 {[%clk 0:00:07.3]} 54. Kh3 {[%clk 0:00:05.7]} 54... Kf5 {[%clk 0:00:07.2]} 55. Kg2 {[%clk 0:00:05.6]} 55... g4 {[%clk 0:00:07.1]} 56. Kh2 {[%clk 0:00:05.5]} 56... Kg5 {[%clk 0:00:07]} 57. Kg2 {[%clk 0:00:05.4]} 57... h4 {[%clk 0:00:06.9]} 58. Kh2 {[%clk 0:00:05.3]} 58... Kf4 {[%clk 0:00:06.8]} 59. Kg2 {[%clk 0:00:04.8]} 59... g3 {[%clk 0:00:06.7]} 60. Kg1 {[%clk 0:00:04.7]} 60... Kg4 {[%clk 0:00:06.6]} 0-1\n",
    "time_control": "60",
    "end_time": 1655942001,
    "rated": true,
    "accuracies": {
      "white": 61.54,
      "black": 79.05
    },
    "tcn": "mC0Kgv5QfA9Ieg!Tfe8!ksTCeCZJvKJCK1IngnQKngK1ltCtcD6Lbl!?dN1RAJLUNEYQJv7PghPjabjspFRAFNULEM3VM0480IXHvQ86lAsAIAHAQHtlDlLbls9LHZLNhgbLZHLSHONMO6S6gnMUow6XnuUOuBOiBAiosBowBKwEAI?3IRVNKBX6BK6LKDLURKEDKD3VDwU1wx2MxwVUwxULxoMEopLMpoNFopMDpoEwogDE",
    "uuid": "3671320d-f286-11ec-8e7a-78ac4409ff3c",
    "initial_setup": "rnbqkbnr/pppppppp/8/8/8/8/PPPPPPPP/RNBQKBNR w KQkq - 0 1",
    "fen": "8/p4b2/8/8/6kp/6p1/8/6K1 w - -",
    "time_class": "bullet",
    "rules": "chess",
    "white": {
      "rating": 3125,
      "result": "timeout",
      "@id": "https://api.chess.com/pub/player/0gzpanda",
      "username": "0gZPanda",
      "uuid": "a52051ea-630e-11ea-88cb-478d6d4098ea"
    },
    "black": {
      "rating": 3210,
      "result": "win",
      "@id": "https://api.chess.com/pub/player/penguingm1",
      "username": "penguingm1",
      "uuid": "332537e0-d833-11e1-8022-000000000000"
    }
  },
  {
    "url": "https://www.chess.com/game/live/49681141055",
    "pgn": "[Event \"Live Chess\"]\n[Site \"Chess.com\"]\n[Date \"2022.06.22\"]\n[Round \"-\"]\n[White \"penguingm1\"]\n[Black \"0gZPanda\"]\n[Result \"0-1\"]\n[CurrentPosition \"8/p3rkpp/R7/2bn4/1p6/1P3K1P/P5P1/8 w - -\"]\n[Timezone \"UTC\"]\n[ECO \"D35\"]\n[ECOUrl \"https://www.chess.com/openings/Queens-Gambit-Declined-Queens-Knight-Variation-3...Nf6\"]\n[UTCDate \"2022.06.22\"]\n[UTCTime \"23:53:16\"]\n[WhiteElo \"3198\"]\n[BlackElo \"3135\"]\n[TimeControl \"60\"]\n[Termination \"0gZPanda won by resignation\"]\n[StartTime \"23:53:16\"]\n[EndDate \"2022.06.22\"]\n[EndTime \"23:54:40\"]\n[Link \"https://www.chess.com/game/live/49681141055\"]\n\n1. d4 {[%clk 0:01:00]} 1... Nf6 {[%clk 0:01:00]} 2. c4 {[%clk 0:00:59.6]} 2... e6 {[%clk 0:00:59.3]} 3. Nc3 {[%clk 0:00:59.3]} 3... d5 {[%clk 0:00:59]} 4. cxd5 {[%clk 0:00:59.2]} 4... exd5 {[%clk 0:00:58.9]} 5. Bg5 {[%clk 0:00:58.6]} 5... Be7 {[%clk 0:00:58.5]} 6. e3 {[%clk 0:00:58.3]} 6... O-O {[%clk 0:00:58.2]} 7. Bd3 {[%clk 0:00:57.7]} 7... c6 {[%clk 0:00:58]} 8. Qc2 {[%clk 0:00:57.4]} 8... Nbd7 {[%clk 0:00:57.6]} 9. Nge2 {[%clk 0:00:57.1]} 9... Re8 {[%clk 0:00:57.3]} 10. O-O {[%clk 0:00:56.8]} 10... Nf8 {[%clk 0:00:57.1]} 11. f3 {[%clk 0:00:56.5]} 11... Ng6 {[%clk 0:00:55]} 12. Rad1 {[%clk 0:00:55.7]} 12... b5 {[%clk 0:00:51.9]} 13. e4 {[%clk 0:00:54.7]} 13... b4 {[%clk 0:00:51.3]} 14. Na4 {[%clk 0:00:53.3]} 14... dxe4 {[%clk 0:00:51]} 15. fxe4 {[%clk 0:00:52.9]} 15... Nxe4 {[%clk 0:00:50.7]} 16. Bxe4 {[%clk 0:00:50.2]} 16... Bxg5 {[%clk 0:00:47.2]} 17. Bxc6 {[%clk 0:00:49.8]} 17... Bg4 {[%clk 0:00:44.1]} 18. Bxe8 {[%clk 0:00:47.6]} 18... Qxe8 {[%clk 0:00:43.9]} 19. Rde1 {[%clk 0:00:46.9]} 19... Rc8 {[%clk 0:00:43.2]} 20. Qd3 {[%clk 0:00:43.9]} 20... Qxa4 {[%clk 0:00:41.8]} 21. Ng3 {[%clk 0:00:41.2]} 21... Qd7 {[%clk 0:00:40.8]} 22. h3 {[%clk 0:00:40.1]} 22... Be6 {[%clk 0:00:40.2]} 23. Ne4 {[%clk 0:00:39.8]} 23... Be7 {[%clk 0:00:39.4]} 24. Qe3 {[%clk 0:00:38.3]} 24... Rd8 {[%clk 0:00:38.2]} 25. Nc5 {[%clk 0:00:37]} 25... Qxd4 {[%clk 0:00:36.1]} 26. Nxe6 {[%clk 0:00:36.4]} 26... fxe6 {[%clk 0:00:34.5]} 27. Qxd4 {[%clk 0:00:35.4]} 27... Rxd4 {[%clk 0:00:34.4]} 28. Rxe6 {[%clk 0:00:35.1]} 28... Rd7 {[%clk 0:00:32.6]} 29. Rc1 {[%clk 0:00:34]} 29... Kf7 {[%clk 0:00:31.8]} 30. Ra6 {[%clk 0:00:33.5]} 30... Bf6 {[%clk 0:00:30.9]} 31. b3 {[%clk 0:00:32.4]} 31... Nf4 {[%clk 0:00:30]} 32. Rc4 {[%clk 0:00:31.4]} 32... Nd5 {[%clk 0:00:28.9]} 33. Kf2 {[%clk 0:00:29.6]} 33... Re7 {[%clk 0:00:28.2]} 34. Rc5 {[%clk 0:00:28.1]} 34... Bd4+ {[%clk 0:00:27.4]} 35. Kf3 {[%clk 0:00:27.7]} 35... Bxc5 {[%clk 0:00:27]} 0-1\n",
    "time_control": "60",
    "end_time": 1655942080,
    "rated": true,
    "accuracies": {
      "white": 80.81,
      "black": 85.37
    },
    "tcn": "lB!TkA0SbsZJAJSJcM90mu8!ftYQdk5Zgm98egZ9nv9UadXHuCHzsyJCvCTCtC0MCQ6EQ878de46kt8ymwyZpxESwCM0tu67CIZBIS1SuB7BeSBZfc!1SO0TjrUDcADJgnZ0AITBnvBI",
    "uuid": "825e4c45-f286-11ec-8e7a-78ac4409ff3c",
    "initial_setup": "rnbqkbnr/pppppppp/8/8/8/8/PPPPPPPP/RNBQKBNR w KQkq - 0 1",
    "fen": "8/p3rkpp/R7/2bn4/1p6/1P3K1P/P5P1/8 w - -",
    "time_class": "bullet",
    "rules": "chess",
    "white": {
      "rating": 3198,
      "result": "resigned",
      "@id": "https://api.chess.com/pub/player/penguingm1",
      "username": "penguingm1",
      "uuid": "332537e0-d833-11e1-8022-000000000000"
    },
    "black": {
      "rating": 3135,
      "result": "win",
      "@id": "https://api.chess.com/pub/player/0gzpanda",
      "username": "0gZPanda",
      "uuid": "a52051ea-630e-11ea-88cb-478d6d4098ea"
    }
  },
  {
    "url": "https://www.chess.com/game/live/49681153089",
    "pgn": "[Event \"Live Chess\"]\n[Site \"Chess.com\"]\n[Date \"2022.06.22\"]\n[Round \"-\"]\n[White \"0gZPanda\"]\n[Black \"penguingm1\"]\n[Result \"1-0\"]\n[CurrentPosition \"2B5/8/5pk1/8/3B4/4P1PK/8/7R b - -\"]\n[Timezone \"UTC\"]\n[ECO \"C64\"]\n[ECOUrl \"https://www.chess.com/openings/Ruy-Lopez-Opening-Classical-Defense-4.O-O-Qf6\"]\n[UTCDate \"2022.06.22\"]\n[UTCTime \"23:54:24\"]\n[WhiteElo \"3144\"]\n[BlackElo \"3187\"]\n[TimeControl \"60\"]\n[Termination \"0gZPanda won by resignation\"]\n[StartTime \"23:54:24\"]\n[EndDate \"2022.06.22\"]\n[EndTime \"23:56:36\"]\n[Link \"https://www.chess.com/game/live/49681153089\"]\n\n1. e4 {[%clk 0:01:00]} 1... e5 {[%clk 0:00:59.6]} 2. Nf3 {[%clk 0:00:59]} 2... Nc6 {[%clk 0:00:59.3]} 3. Bb5 {[%clk 0:00:58.7]} 3... Bc5 {[%clk 0:00:58.5]} 4. O-O {[%clk 0:00:57.8]} 4... Qf6 {[%clk 0:00:57.9]} 5. Nc3 {[%clk 0:00:56.9]} 5... Nge7 {[%clk 0:00:57.6]} 6. Nd5 {[%clk 0:00:56.4]} 6... Nxd5 {[%clk 0:00:57.2]} 7. exd5 {[%clk 0:00:55.9]} 7... Nd4 {[%clk 0:00:57.1]} 8. Nxd4 {[%clk 0:00:55.5]} 8... Bxd4 {[%clk 0:00:57]} 9. c3 {[%clk 0:00:55.1]} 9... Bb6 {[%clk 0:00:56.9]} 10. d4 {[%clk 0:00:54.8]} 10... exd4 {[%clk 0:00:55.8]} 11. Re1+ {[%clk 0:00:54.4]} 11... Kf8 {[%clk 0:00:55.4]} 12. c4 {[%clk 0:00:54.1]} 12... Bc5 {[%clk 0:00:54.1]} 13. Bd2 {[%clk 0:00:53.1]} 13... c6 {[%clk 0:00:53.1]} 14. b4 {[%clk 0:00:52.1]} 14... Bd6 {[%clk 0:00:50.9]} 15. c5 {[%clk 0:00:51.2]} 15... Be5 {[%clk 0:00:49.6]} 16. Bf1 {[%clk 0:00:49.2]} 16... d6 {[%clk 0:00:47.5]} 17. dxc6 {[%clk 0:00:48.3]} 17... bxc6 {[%clk 0:00:47.4]} 18. cxd6 {[%clk 0:00:47.8]} 18... Bxd6 {[%clk 0:00:46.2]} 19. Rc1 {[%clk 0:00:46.5]} 19... Bd7 {[%clk 0:00:45.5]} 20. Qh5 {[%clk 0:00:44]} 20... Re8 {[%clk 0:00:43.8]} 21. Rxe8+ {[%clk 0:00:42.9]} 21... Bxe8 {[%clk 0:00:43.5]} 22. Bd3 {[%clk 0:00:42.3]} 22... h6 {[%clk 0:00:43.1]} 23. Re1 {[%clk 0:00:41.2]} 23... Bd7 {[%clk 0:00:42.3]} 24. Qa5 {[%clk 0:00:40.6]} 24... g6 {[%clk 0:00:41.2]} 25. Qxa7 {[%clk 0:00:39.5]} 25... Be6 {[%clk 0:00:40]} 26. Qa8+ {[%clk 0:00:38.6]} 26... Kg7 {[%clk 0:00:39.7]} 27. Qxc6 {[%clk 0:00:38.2]} 27... Rd8 {[%clk 0:00:39.5]} 28. b5 {[%clk 0:00:37.2]} 28... Bxa2 {[%clk 0:00:37.6]} 29. g3 {[%clk 0:00:36.3]} 29... h5 {[%clk 0:00:36.4]} 30. b6 {[%clk 0:00:35.3]} 30... h4 {[%clk 0:00:36.1]} 31. b7 {[%clk 0:00:34.8]} 31... hxg3 {[%clk 0:00:35.7]} 32. hxg3 {[%clk 0:00:34.7]} 32... Be6 {[%clk 0:00:33.1]} 33. Qxd6 {[%clk 0:00:33.6]} 33... Rxd6 {[%clk 0:00:32.7]} 34. b8=Q {[%clk 0:00:33]} 34... Rd5 {[%clk 0:00:32.6]} 35. Bb4 {[%clk 0:00:31.6]} 35... Rh5 {[%clk 0:00:30.8]} 36. Qf8+ {[%clk 0:00:30.9]} 36... Kh7 {[%clk 0:00:30.5]} 37. Be4 {[%clk 0:00:28.4]} 37... d3 {[%clk 0:00:28.6]} 38. Qd6 {[%clk 0:00:24.9]} 38... Qg5 {[%clk 0:00:24.2]} 39. Qxd3 {[%clk 0:00:23.8]} 39... Qh6 {[%clk 0:00:23.9]} 40. Bg2 {[%clk 0:00:22.9]} 40... Rf5 {[%clk 0:00:21.7]} 41. Bc3 {[%clk 0:00:22.1]} 41... Qf8 {[%clk 0:00:20.6]} 42. Be4 {[%clk 0:00:20.8]} 42... Rh5 {[%clk 0:00:19.5]} 43. Bf3 {[%clk 0:00:20.3]} 43... Rf5 {[%clk 0:00:19.2]} 44. Kg2 {[%clk 0:00:19.8]} 44... Kg8 {[%clk 0:00:15.6]} 45. Rh1 {[%clk 0:00:19.3]} 45... f6 {[%clk 0:00:15.3]} 46. Be4 {[%clk 0:00:18.2]} 46... Rg5 {[%clk 0:00:13.8]} 47. Bxg6 {[%clk 0:00:17.4]} 47... Qe7 {[%clk 0:00:12.3]} 48. Be4 {[%clk 0:00:16.9]} 48... Bf7 {[%clk 0:00:11.6]} 49. Bf3 {[%clk 0:00:15.7]} 49... Kg7 {[%clk 0:00:11.1]} 50. Qe3 {[%clk 0:00:14.9]} 50... Qxe3 {[%clk 0:00:10.1]} 51. fxe3 {[%clk 0:00:14.6]} 51... Rc5 {[%clk 0:00:09.7]} 52. Bd4 {[%clk 0:00:14]} 52... Rc2+ {[%clk 0:00:09.6]} 53. Kh3 {[%clk 0:00:13.5]} 53... Be6+ {[%clk 0:00:09.2]} 54. Bg4 {[%clk 0:00:13.2]} 54... Kg6 {[%clk 0:00:09]} 55. Bxe6 {[%clk 0:00:12.5]} 55... Rc8 {[%clk 0:00:08.8]} 56. Bxc8 {[%clk 0:00:11.4]} 1-0\n",
    "time_control": "60",
    "end_time": 1655942196,
    "rated": true,
    "accuracies": {
      "white": 81,
      "black": 73.15
    },
    "tcn": "mC0Kgv5QfH9Ieg7Tbs!0sJ0JCJQBvBIBksBPlBKBfe89sAPIclYQjzIRAIRKHfZRJQXQIRKRac6ZdN48e8Z8ft3Vce8ZNG2UGWZSW4924Q?7zHSiowVNHPNFPXFwpwiSQR7RX~RJlzJN5923tCBt9RTMRtMVCoNLzsV9oCLNCvNLgo3!eh1TvCLMCU90UCS1Cv!2tu0unuMIsBIkox1SvE2UESk6S6",
    "uuid": "af0d33c5-f286-11ec-8e7a-78ac4409ff3c",
    "initial_setup": "rnbqkbnr/pppppppp/8/8/8/8/PPPPPPPP/RNBQKBNR w KQkq - 0 1",
    "fen": "2B5/8/5pk1/8/3B4/4P1PK/8/7R b - -",
    "time_class": "bullet",
    "rules": "chess",
    "white": {
      "rating": 3144,
      "result": "win",
      "@id": "https://api.chess.com/pub/player/0gzpanda",
      "username": "0gZPanda",
      "uuid": "a52051ea-630e-11ea-88cb-478d6d4098ea"
    },
    "black": {
      "rating": 3187,
      "result": "resigned",
      "@id": "https://api.chess.com/pub/player/penguingm1",
      "username": "penguingm1",
      "uuid": "332537e0-d833-11e1-8022-000000000000"
    }
  },
  {
    "url": "https://www.chess.com/game/live/49681172239",
    "pgn": "[Event \"Live Chess\"]\n[Site \"Chess.com\"]\n[Date \"2022.06.22\"]\n[Round \"-\"]\n[White \"penguingm1\"]\n[Black \"xutopia\"]\n[Result \"1-0\"]\n[CurrentPosition \"r5k1/1p3p2/pn1p2p1/2pP3p/2P1rBb1/2P1N1Pq/3Q1R1P/R4BK1 b - -\"]\n[Timezone \"UTC\"]\n[ECO \"E61\"]\n[ECOUrl \"https://www.chess.com/openings/Kings-Indian-Defense-Normal-Variation\"]\n[UTCDate \"2022.06.22\"]\n[UTCTime \"23:56:33\"]\n[WhiteElo \"2928\"]\n[BlackElo \"1776\"]\n[TimeControl \"180\"]\n[Termination \"penguingm1 won by resignation\"]\n[StartTime \"23:56:33\"]\n[EndDate \"2022.06.22\"]\n[EndTime \"23:59:41\"]\n[Link \"https://www.chess.com/game/live/49681172239\"]\n\n1. d4 {[%clk 0:03:00]} 1... g6 {[%clk 0:03:00]} 2. c4 {[%clk 0:02:58.8]} 2... Bg7 {[%clk 0:02:59]} 3. Nc3 {[%clk 0:02:58.4]} 3... Nf6 {[%clk 0:02:57.5]} 4. e4 {[%clk 0:02:58]} 4... d6 {[%clk 0:02:56.6]} 5. Nge2 {[%clk 0:02:57.7]} 5... O-O {[%clk 0:02:55.5]} 6. f3 {[%clk 0:02:57.5]} 6... Nc6 {[%clk 0:02:54.5]} 7. Be3 {[%clk 0:02:56.3]} 7... Re8 {[%clk 0:02:49.6]} 8. Qd2 {[%clk 0:02:54.6]} 8... h5 {[%clk 0:02:47.6]} 9. d5 {[%clk 0:02:43.8]} 9... Ne5 {[%clk 0:02:44.3]} 10. Nd4 {[%clk 0:02:39.5]} 10... c5 {[%clk 0:02:35.6]} 11. Nc2 {[%clk 0:02:37]} 11... a6 {[%clk 0:02:28]} 12. a4 {[%clk 0:02:35.8]} 12... Ned7 {[%clk 0:02:25.5]} 13. Be2 {[%clk 0:02:34.2]} 13... Nb6 {[%clk 0:02:14.6]} 14. O-O {[%clk 0:02:30]} 14... Nfd7 {[%clk 0:02:02.6]} 15. f4 {[%clk 0:02:27.8]} 15... e5 {[%clk 0:01:55.1]} 16. a5 {[%clk 0:02:23.3]} 16... exf4 {[%clk 0:01:48.6]} 17. Bxf4 {[%clk 0:02:22.7]} 17... Bxc3 {[%clk 0:01:29.2]} 18. bxc3 {[%clk 0:02:20.8]} 18... Rxe4 {[%clk 0:01:28]} 19. axb6 {[%clk 0:02:19.4]} 19... Nxb6 {[%clk 0:01:26.1]} 20. Ne3 {[%clk 0:02:18.3]} 20... Qh4 {[%clk 0:01:17.8]} 21. g3 {[%clk 0:02:15.2]} 21... Qh3 {[%clk 0:01:09.3]} 22. Rf2 {[%clk 0:02:13]} 22... Bg4 {[%clk 0:01:02.4]} 23. Bf1 {[%clk 0:02:12]} 1-0\n",
    "time_control": "180",
    "end_time": 1655942381,
    "rated": true,
    "accuracies": {
      "white": 83.48,
      "black": 72.95
    },
    "tcn": "lB2UkA92bs!TmCZRgm8!nv5Qcu98dl3NBJQKmBYIBkWOiyKZfmZPegTZvD0KyGKDuD2sjs8CGPZPku7FowFxfn6Emf",
    "uuid": "f45911ad-f286-11ec-8e7a-78ac4409ff3c",
    "initial_setup": "rnbqkbnr/pppppppp/8/8/8/8/PPPPPPPP/RNBQKBNR w KQkq - 0 1",
    "fen": "r5k1/1p3p2/pn1p2p1/2pP3p/2P1rBb1/2P1N1Pq/3Q1R1P/R4BK1 b - -",
    "time_class": "blitz",
    "rules": "chess",
    "white": {
      "rating": 2928,
      "result": "win",
      "@id": "https://api.chess.com/pub/player/penguingm1",
      "username": "penguingm1",
      "uuid": "332537e0-d833-11e1-8022-000000000000"
    },
    "black": {
      "rating": 1776,
      "result": "resigned",
      "@id": "https://api.chess.com/pub/player/xutopia",
      "username": "xutopia",
      "uuid": "f5369496-9891-11e6-802c-000000000000"
    }
  }
]