{
    "avatar": "https://images.chesscomfiles.com/uploads/v1/user/16650508.13d7746b.200x200o.28794309ae1c.jpeg",
    "player_id": 16650508,
    "@id": "https://api.chess.com/pub/player/lasker_fiverr",
    "url": "https://www.chess.com/member/Lasker_Fiverr",
    "name": "Lukajic Bojan",
    "username": "lasker_fiverr",
    "title": "NM",
    "followers": 477,
    "country": "https://api.chess.com/pub/country/RS",
    "location": "Novi Sad",
    "last_online": 1741622176,
    "joined": 1396005568,
    "status": "premium",
    "is_streamer": false,
    "verified": false,
    "league": "Stone",
    "streaming_platforms": [],
    "chess_daily": {
        "last": {
            "rating": 1871,
            "date": 1739628357,
            "rd": 258
        },
        "best": {
            "rating": 2000,
            "date": 1396005568,
            "game": "https://www.chess.com/game/daily/728486977"
        },
        "record": {
            "win": 4,
            "loss": 0,
            "draw": 0,
            "time_per_move": 16545,
            "timeout_percent": 0
        }
    },
    "chess_rapid": {
        "last": {
            "rating": 1832,
            "date": 1731430588,
            "rd": 95
        },
        "best": {
            "rating": 2045,
            "date": 1688592553,
            "game": "https://www.chess.com/game/live/57439738277"
        },
        "record": {
            "win": 1153,
            "loss": 53,
            "draw": 102
        }
    },
    "chess_bullet": {
        "last": {
            "rating": 1290,
            "date": 1641329301,
            "rd": 180
        },
        "best": {
            "rating": 2000,
            "date": 1429599600,
            "game": "https://www.chess.com/game/live/24310858725"
        },
        "record": {
            "win": 3,
            "loss": 4,
            "draw": 0
        }
    },
    "chess_blitz": {
        "last": {
            "rating": 2200,
            "date": 1731431020,
            "rd": 211
        },
        "best": {
            "rating": 2200,
            "date": 1731431020,
            "game": "https://www.chess.com/game/live/3061842629"
        },
        "record": {
            "win": 1191,
            "loss": 326,
            "draw": 94
        }
    },
    "fide": 2200,
    "tactics": {
        "highest": {
            "rating": 1830,
            "date": 1433874825
        },
        "lowest": {
            "rating": 1765,
            "date": 1713506745
        }
    },
    "puzzle_rush": {}
}