{
    "avatar": "https://images.chesscomfiles.com/uploads/v1/user/31742364.b9d86b50.200x200o.7484e84beefc.jpeg",
    "player_id": 31742364,
    "@id": "https://api.chess.com/pub/player/sina_movahed",
    "url": "https://www.chess.com/member/Sina_Movahed",
    "name": "Sina Movahed",
    "username": "sina_movahed",
    "title": "IM",
    "followers": 1148,
    "country": "https://api.chess.com/pub/country/IR",
    "last_online": 1713193921,
    "joined": 1482212652,
    "status": "premium",
    "is_streamer": false,
    "verified": false,
    "league": "Legend",
    "streaming_platforms": [],
    "chess_daily": {
        "last": {
            "rating": 1769,
            "date": 1724920128,
            "rd": 72
        },
        "best": {
            "rating": 1818,
            "date": 1668206666,
            "game": "https://www.chess.com/game/daily/457100765"
        },
        "record": {
            "win": 34,
            "loss": 7,
            "draw": 3,
            "time_per_move": 32714,
            "timeout_percent": 0
        }
    },
    "chess_rapid": {
        "last": {
            "rating": 2526,
            "date": 1695053851,
            "rd": 78
        },
        "best": {
            "rating": 2564,
            "date": 1679943578,
            "game": "https://www.chess.com/game/live/88788157661"
        },
        "record": {
            "win": 182,
            "loss": 63,
            "draw": 25
        }
    },
    "chess_bullet": {
        "last": {
            "rating": 2859,
            "date": 1713869072,
            "rd": 31
        },
        "best": {
            "rating": 2963,
            "date": 1691612702,
            "game": "https://www.chess.com/game/live/105554944725"
        },
        "record": {
            "win": 995,
            "loss": 571,
            "draw": 64
        }
    },
    "chess_blitz": {
        "last": {
            "rating": 3044,
            "date": 1713869131,
            "rd": 23
        },
        "best": {
            "rating": 3136,
            "date": 1711454266,
            "game": "https://www.chess.com/game/live/100297911437"
        },
        "record": {
            "win": 11057,
            "loss": 8486,
            "draw": 1419
        }
    },
    "fide": 2417,
    "tactics": {
        "highest": {
            "rating": 6643,
            "date": 1700476606
        },
        "lowest": {
            "rating": 576,
            "date": 1496886931
        }
    },
    "puzzle_rush": {
        "best": {
            "total_attempts": 67,
            "score": 64
        }
    }
}