{
    "avatar": "https://images.chesscomfiles.com/uploads/v1/user/36827308.15c0ca5b.200x200o.73e6f66c6c01.jpeg",
    "player_id": 36827308,
    "@id": "https://api.chess.com/pub/player/vaishali2001",
    "url": "https://www.chess.com/member/vaishali2001",
    "name": "Vaishali R",
    "username": "vaishali2001",
    "title": "GM",
    "followers": 1426,
    "country": "https://api.chess.com/pub/country/IN",
    "last_online": 1741256548,
    "joined": 1499318482,
    "status": "premium",
    "is_streamer": false,
    "verified": false,
    "league": "Silver",
    "streaming_platforms": [],
    "chess_daily": {
        "last": {
            "rating": 1230,
            "date": 1714416027,
            "rd": 270
        },
        "best": {
            "rating": 1400,
            "date": 1499318482,
            "game": "https://www.chess.com/game/daily/226602962"
        },
        "record": {
            "win": 2,
            "loss": 0,
            "draw": 2,
            "time_per_move": 202380,
            "timeout_percent": 0
        }
    },
    "chess960_daily": {
        "last": {
            "rating": 1433,
            "date": 1562467203,
            "rd": 326
        },
        "best": {
            "rating": 1433,
            "date": 1562467203,
            "game": "https://www.chess.com/game/daily/226793528"
        },
        "record": {
            "win": 1,
            "loss": 0,
            "draw": 0,
            "time_per_move": 202380,
            "timeout_percent": 0
        }
    },
    "chess_rapid": {
        "last": {
            "rating": 2451,
            "date": 1739820098,
            "rd": 46
        },
        "best": {
            "rating": 2526,
            "date": 1677690887,
            "game": "https://www.chess.com/game/live/71426056023"
        },
        "record": {
            "win": 51,
            "loss": 40,
            "draw": 18
        }
    },
    "chess_bullet": {
        "last": {
            "rating": 2741,
            "date": 1733064632,
            "rd": 48
        },
        "best": {
            "rating": 2777,
            "date": 1623481531,
            "game": "https://www.chess.com/game/live/110050286149"
        },
        "record": {
            "win": 1119,
            "loss": 1661,
            "draw": 201
        }
    },
    "chess_blitz": {
        "last": {
            "rating": 2769,
            "date": 1741258311,
            "rd": 45
        },
        "best": {
            "rating": 2773,
            "date": 1741111741,
            "game": "https://www.chess.com/game/live/133633759601"
        },
        "record": {
            "win": 491,
            "loss": 366,
            "draw": 125
        }
    },
    "tactics": {
        "highest": {
            "rating": 3770,
            "date": 1678963512
        },
        "lowest": {
            "rating": 2183,
            "date": 1536740054
        }
    },
    "puzzle_rush": {
        "best": {
            "total_attempts": 65,
            "score": 62
        }
    }
}