{
    "player_id": 3957680,
    "@id": "https://api.chess.com/pub/player/phishmaster",
    "url": "https://www.chess.com/member/PhishMaster",
    "name": "Kevin Cotreau",
    "username": "phishmaster",
    "title": "NM",
    "followers": 82,
    "country": "https://api.chess.com/pub/country/US",
    "last_online": 1741614151,
    "joined": 1284132922,
    "status": "premium",
    "is_streamer": false,
    "verified": false,
    "league": "Wood",
    "streaming_platforms": [],
    "tactics": {
        "highest": {
            "rating": 3355,
            "date": 1696001459
        },
        "lowest": {
            "rating": 1190,
            "date": 1539572751
        }
    },
    "puzzle_rush": {
        "best": {
            "total_attempts": 30,
            "score": 28
        }
    }
}