{
    "avatar": "https://images.chesscomfiles.com/uploads/v1/user/71320592.2be405ca.200x200o.cdabd5c72323.jpeg",
    "player_id": 71320592,
    "@id": "https://api.chess.com/pub/player/anonymous216756",
    "url": "https://www.chess.com/member/Anonymous216756",
    "username": "anonymous216756",
    "title": "WCM",
    "followers": 2,
    "country": "https://api.chess.com/pub/country/CH",
    "last_online": 1741517786,
    "joined": 1580068803,
    "status": "premium",
    "is_streamer": false,
    "verified": false,
    "league": "Champion",
    "streaming_platforms": [],
    "chess_daily": {
        "last": {
            "rating": 764,
            "date": 1727284663,
            "rd": 177
        },
        "record": {
            "win": 5,
            "loss": 15,
            "draw": 0,
            "time_per_move": 82628,
            "timeout_percent": 0
        }
    },
    "chess_rapid": {
        "last": {
            "rating": 2000,
            "date": 1727284664,
            "rd": 68
        },
        "best": {
            "rating": 1791,
            "date": 1713286968,
            "game": "https://www.chess.com/game/live/99155625825"
        },
        "record": {
            "win": 37,
            "loss": 13,
            "draw": 0
        }
    },
    "chess_bullet": {
        "last": {
            "rating": 2070,
            "date": 1727873569,
            "rd": 33
        },
        "best": {
            "rating": 2106,
            "date": 1727692368,
            "game": "https://www.chess.com/game/live/121435179751"
        },
        "record": {
            "win": 184,
            "loss": 100,
            "draw": 16
        }
    },
    "chess_blitz": {
        "last": {
            "rating": 2194,
            "date": 1739392706,
            "rd": 44
        },
        "best": {
            "rating": 2279,
            "date": 1735506193,
            "game": "https://www.chess.com/game/live/131563762889"
        },
        "record": {
            "win": 603,
            "loss": 451,
            "draw": 62
        }
    },
    "tactics": {
        "highest": {
            "rating": 3299,
            "date": 1737820125
        },
        "lowest": {
            "rating": 414,
            "date": 1580132488
        }
    },
    "puzzle_rush": {
        "best": {
            "total_attempts": 55,
            "score": 52
        }
    }
}