{
    "avatar": "https://images.chesscomfiles.com/uploads/v1/user/76856206.c3dce4ae.200x200o.cf019fe84b1e.jpeg",
    "player_id": 76856206,
    "@id": "https://api.chess.com/pub/player/matenkatz",
    "url": "https://www.chess.com/member/Matenkatz",
    "name": "Stay Focused",
    "username": "matenkatz",
    "title": "GM",
    "followers": 16,
    "country": "https://api.chess.com/pub/country/RU",
    "location": "\u0421\u0430\u043d\u043a\u0442-\u041f\u0435\u0442\u0435\u0440\u0431\u0443\u0440\u0433",
    "last_online": 1593693764,
    "joined": 1587021842,
    "status": "premium",
    "is_streamer": false,
    "verified": false,
    "streaming_platforms": [],
    "chess_bullet": {
        "last": {
            "rating": 2350,
            "date": 1595348243,
            "rd": 21
        },
        "best": {
            "rating": 2888,
            "date": 1593561205,
            "game": "https://www.chess.com/game/live/5082283274"
        },
        "record": {
            "win": 444,
            "loss": 149,
            "draw": 28
        }
    },
    "chess_blitz": {
        "last": {
            "rating": 2200,
            "date": 1595348243,
            "rd": 75
        },
        "best": {
            "rating": 3018,
            "date": 1593549542,
            "game": "https://www.chess.com/game/live/4902860628"
        },
        "record": {
            "win": 28,
            "loss": 1,
            "draw": 5
        }
    },
    "fide": 2611,
    "tactics": {
        "highest": {
            "rating": 2707,
            "date": 1592456229
        },
        "lowest": {
            "rating": 2564,
            "date": 1592455218
        }
    },
    "puzzle_rush": {}
}