{
    "avatar": "https://images.chesscomfiles.com/uploads/v1/user/9117260.693447a6.200x200o.6e8ac3365d49.jpeg",
    "player_id": 9117260,
    "@id": "https://api.chess.com/pub/player/fy_rakotomaharo",
    "url": "https://www.chess.com/member/Fy_Rakotomaharo",
    "name": "Fy Antenaina Rakotomaharo",
    "username": "fy_rakotomaharo",
    "title": "IM",
    "followers": 458,
    "country": "https://api.chess.com/pub/country/MG",
    "location": "Antananarivo",
    "last_online": 1741700866,
    "joined": 1349200139,
    "status": "premium",
    "is_streamer": false,
    "verified": false,
    "league": "Silver",
    "streaming_platforms": [],
    "chess_daily": {
        "last": {
            "rating": 1260,
            "date": 1643448494,
            "rd": 179
        },
        "best": {
            "rating": 1260,
            "date": 1611876755,
            "game": "https://www.chess.com/game/daily/285337452"
        },
        "record": {
            "win": 7,
            "loss": 8,
            "draw": 0,
            "time_per_move": 25089,
            "timeout_percent": 0
        }
    },
    "chess_rapid": {
        "last": {
            "rating": 2510,
            "date": 1714382065,
            "rd": 50
        },
        "best": {
            "rating": 2548,
            "date": 1693850950,
            "game": "https://www.chess.com/game/live/77914859167"
        },
        "record": {
            "win": 34,
            "loss": 9,
            "draw": 4
        }
    },
    "chess_bullet": {
        "last": {
            "rating": 2747,
            "date": 1734886125,
            "rd": 49
        },
        "best": {
            "rating": 2755,
            "date": 1605002053,
            "game": "https://www.chess.com/game/live/5718186657"
        },
        "record": {
            "win": 251,
            "loss": 217,
            "draw": 23
        }
    },
    "chess_blitz": {
        "last": {
            "rating": 2785,
            "date": 1735667049,
            "rd": 47
        },
        "best": {
            "rating": 2807,
            "date": 1733248621,
            "game": "https://www.chess.com/game/live/129401045075"
        },
        "record": {
            "win": 2335,
            "loss": 2183,
            "draw": 418
        }
    },
    "fide": 2422,
    "tactics": {
        "highest": {
            "rating": 3145,
            "date": 1681507074
        },
        "lowest": {
            "rating": 1331,
            "date": 1351591903
        }
    },
    "puzzle_rush": {
        "best": {
            "total_attempts": 47,
            "score": 44
        }
    }
}