{
    "player_id": 108636298,
    "@id": "https://api.chess.com/pub/player/jestemlepszyxd",
    "url": "https://www.chess.com/member/JestemLepszyXD",
    "username": "jestemlepszyxd",
    "title": "GM",
    "followers": 5,
    "country": "https://api.chess.com/pub/country/PL",
    "last_online": 1703892493,
    "joined": 1609439433,
    "status": "premium",
    "is_streamer": false,
    "verified": false,
    "league": "Crystal",
    "streaming_platforms": [],
    "chess_rapid": {
        "last": {
            "rating": 1441,
            "date": 1609676922,
            "rd": 78
        },
        "best": {
            "rating": 1441,
            "date": 1609676922,
            "game": "https://www.chess.com/game/live/6121464395"
        },
        "record": {
            "win": 22,
            "loss": 0,
            "draw": 0
        }
    },
    "chess_bullet": {
        "last": {
            "rating": 2810,
            "date": 1697619783,
            "rd": 40
        },
        "best": {
            "rating": 2894,
            "date": 1696909332,
            "game": "https://www.chess.com/game/live/89704144971"
        },
        "record": {
            "win": 226,
            "loss": 41,
            "draw": 2
        }
    },
    "chess_blitz": {
        "last": {
            "rating": 2851,
            "date": 1701236480,
            "rd": 41
        },
        "best": {
            "rating": 2937,
            "date": 1699073634,
            "game": "https://www.chess.com/game/live/91362011707"
        },
        "record": {
            "win": 216,
            "loss": 60,
            "draw": 7
        }
    },
    "tactics": {
        "highest": {
            "rating": 400,
            "date": 1609439433
        },
        "lowest": {
            "rating": 400,
            "date": 1609439433
        }
    },
    "puzzle_rush": {}
}