{
    "avatar": "https://images.chesscomfiles.com/uploads/v1/user/195520963.01f639d6.200x200o.0153b11630b1.jpg",
    "player_id": 195520963,
    "@id": "https://api.chess.com/pub/player/themandaiorian",
    "url": "https://www.chess.com/member/TheMandaIorian",
    "name": "Din Djarin",
    "username": "themandaiorian",
    "title": "IM",
    "followers": 70,
    "country": "https://api.chess.com/pub/country/XX",
    "location": "Mines of Mandalore",
    "last_online": 1741283833,
    "joined": 1662033142,
    "status": "premium",
    "is_streamer": false,
    "verified": false,
    "league": "Champion",
    "streaming_platforms": [],
    "chess_bullet": {
        "last": {
            "rating": 2792,
            "date": 1734956469,
            "rd": 47
        },
        "best": {
            "rating": 2860,
            "date": 1674162174,
            "game": "https://www.chess.com/game/live/64098842011"
        },
        "record": {
            "win": 13,
            "loss": 3,
            "draw": 0
        }
    },
    "chess_blitz": {
        "last": {
            "rating": 2967,
            "date": 1741284125,
            "rd": 31
        },
        "best": {
            "rating": 3110,
            "date": 1735513854,
            "game": "https://www.chess.com/game/live/122834743685"
        },
        "record": {
            "win": 809,
            "loss": 740,
            "draw": 188
        }
    },
    "tactics": {
        "highest": {
            "rating": 1000,
            "date": 1662033142
        },
        "lowest": {
            "rating": 1000,
            "date": 1662033142
        }
    },
    "puzzle_rush": {
        "best": {
            "total_attempts": 54,
            "score": 51
        }
    }
}