{
    "avatar": "https://images.chesscomfiles.com/uploads/v1/user/312839891.c54f7af9.200x200o.36514d5510af.jpg",
    "player_id": 312839891,
    "@id": "https://api.chess.com/pub/player/baylavchess",
    "url": "https://www.chess.com/member/BaylavChess",
    "name": "Can Baylav",
    "username": "baylavchess",
    "title": "NM",
    "followers": 41,
    "country": "https://api.chess.com/pub/country/TR",
    "location": "Ankara",
    "last_online": 1741472503,
    "joined": 1694728059,
    "status": "premium",
    "is_streamer": false,
    "verified": false,
    "league": "Crystal",
    "streaming_platforms": [],
    "chess_rapid": {
        "last": {
            "rating": 2444,
            "date": 1703347253,
            "rd": 349
        },
        "best": {
            "rating": 2444,
            "date": 1703347253,
            "game": "https://www.chess.com/game/live/97086051001"
        },
        "record": {
            "win": 1,
            "loss": 0,
            "draw": 0
        }
    },
    "chess_bullet": {
        "last": {
            "rating": 2501,
            "date": 1741372095,
            "rd": 37
        },
        "best": {
            "rating": 2595,
            "date": 1721823922,
            "game": "https://www.chess.com/game/live/132174053613"
        },
        "record": {
            "win": 214,
            "loss": 185,
            "draw": 24
        }
    },
    "chess_blitz": {
        "last": {
            "rating": 2384,
            "date": 1741479036,
            "rd": 39
        },
        "best": {
            "rating": 2515,
            "date": 1736108986,
            "game": "https://www.chess.com/game/live/115485588879"
        },
        "record": {
            "win": 322,
            "loss": 257,
            "draw": 33
        }
    },
    "fide": 0,
    "tactics": {
        "highest": {
            "rating": 3167,
            "date": 1735560514
        },
        "lowest": {
            "rating": 400,
            "date": 1694728059
        }
    },
    "puzzle_rush": {
        "best": {
            "total_attempts": 63,
            "score": 60
        }
    }
}