{
    "player_id": 330179615,
    "@id": "https://api.chess.com/pub/player/matapatos593",
    "url": "https://www.chess.com/member/Matapatos593",
    "username": "matapatos593",
    "title": "CM",
    "followers": 5,
    "country": "https://api.chess.com/pub/country/US",
    "last_online": 1737332892,
    "joined": 1701621381,
    "status": "premium",
    "is_streamer": false,
    "verified": false,
    "league": "Elite",
    "streaming_platforms": [],
    "chess_blitz": {
        "last": {
            "rating": 2258,
            "date": 1735336341,
            "rd": 51
        },
        "best": {
            "rating": 2377,
            "date": 1703764718,
            "game": "https://www.chess.com/game/live/97251121221"
        },
        "record": {
            "win": 673,
            "loss": 734,
            "draw": 112
        }
    },
    "fide": 2280,
    "tactics": {
        "highest": {
            "rating": 1000,
            "date": 1701621381
        },
        "lowest": {
            "rating": 1000,
            "date": 1701621381
        }
    },
    "puzzle_rush": {}
}