{
    "avatar": "https://images.chesscomfiles.com/uploads/v1/user/51159440.eb6b90b5.200x200o.43dc97535a6d.png",
    "player_id": 51159440,
    "@id": "https://api.chess.com/pub/player/chessialist",
    "url": "https://www.chess.com/member/Chessialist",
    "name": "K\u0131van\u00e7 Haznedaro\u011flu",
    "username": "chessialist",
    "title": "GM",
    "followers": 567,
    "country": "https://api.chess.com/pub/country/TR",
    "last_online": 1703854876,
    "joined": 1540557644,
    "status": "premium",
    "is_streamer": false,
    "verified": false,
    "league": "Elite",
    "streaming_platforms": [],
    "chess_rapid": {
        "last": {
            "rating": 2346,
            "date": 1658164309,
            "rd": 104
        },
        "best": {
            "rating": 2551,
            "date": 1593280147,
            "game": "https://www.chess.com/game/live/4924804353"
        },
        "record": {
            "win": 19,
            "loss": 16,
            "draw": 10
        }
    },
    "chess_bullet": {
        "last": {
            "rating": 2503,
            "date": 1638278439,
            "rd": 44
        },
        "best": {
            "rating": 2557,
            "date": 1638219055,
            "game": "https://www.chess.com/game/live/3587932544"
        },
        "record": {
            "win": 59,
            "loss": 61,
            "draw": 7
        }
    },
    "chess_blitz": {
        "last": {
            "rating": 2657,
            "date": 1701096829,
            "rd": 41
        },
        "best": {
            "rating": 2935,
            "date": 1638303452,
            "game": "https://www.chess.com/game/live/33082153405"
        },
        "record": {
            "win": 1526,
            "loss": 1088,
            "draw": 307
        }
    },
    "fide": 2472,
    "tactics": {
        "highest": {
            "rating": 3567,
            "date": 1679986945
        },
        "lowest": {
            "rating": 2391,
            "date": 1541358913
        }
    },
    "puzzle_rush": {
        "best": {
            "total_attempts": 54,
            "score": 51
        }
    }
}