{
    "avatar": "https://images.chesscomfiles.com/uploads/v1/user/52063362.ac2d2c6a.200x200o.cc40ea8d3101.jpeg",
    "player_id": 52063362,
    "@id": "https://api.chess.com/pub/player/yaryi_sergey",
    "url": "https://www.chess.com/member/Yaryi_sergey",
    "name": "\u0421\u0435\u0440\u0433\u0435\u0439 \u042f\u0440\u044b\u0439",
    "username": "yaryi_sergey",
    "title": "FM",
    "followers": 17,
    "country": "https://api.chess.com/pub/country/RU",
    "location": "\u0420\u0435\u0441\u043f\u0443\u0431\u043b\u0438\u043a\u0430 \u041a\u0440\u044b\u043c",
    "last_online": 1649602244,
    "joined": 1542643969,
    "status": "premium",
    "is_streamer": false,
    "verified": false,
    "league": "Stone",
    "streaming_platforms": [],
    "chess_daily": {
        "last": {
            "rating": 1445,
            "date": 1650702529,
            "rd": 280
        },
        "record": {
            "win": 1,
            "loss": 8,
            "draw": 3,
            "time_per_move": 56509,
            "timeout_percent": 0
        }
    },
    "chess_rapid": {
        "last": {
            "rating": 1806,
            "date": 1645701149,
            "rd": 145
        },
        "best": {
            "rating": 1806,
            "date": 1645701149,
            "game": "https://www.chess.com/game/live/39439727437"
        },
        "record": {
            "win": 14,
            "loss": 2,
            "draw": 1
        }
    },
    "chess_bullet": {
        "last": {
            "rating": 2132,
            "date": 1625772751,
            "rd": 118
        },
        "best": {
            "rating": 2227,
            "date": 1607977553,
            "game": "https://www.chess.com/game/live/4888217644"
        },
        "record": {
            "win": 315,
            "loss": 60,
            "draw": 30
        }
    },
    "chess_blitz": {
        "last": {
            "rating": 2627,
            "date": 1649603481,
            "rd": 39
        },
        "best": {
            "rating": 2709,
            "date": 1648593501,
            "game": "https://www.chess.com/game/live/8447058957"
        },
        "record": {
            "win": 1057,
            "loss": 321,
            "draw": 128
        }
    },
    "fide": 2275,
    "tactics": {
        "highest": {
            "rating": 1283,
            "date": 1641904083
        },
        "lowest": {
            "rating": 400,
            "date": 1614117531
        }
    },
    "puzzle_rush": {
        "best": {
            "total_attempts": 45,
            "score": 42
        }
    }
}